tpms_lib/__init__.py
tpms_lib/example.py
tpms-2.0.1.dist-info/LICENSE
tpms-2.0.1.dist-info/METADATA
tpms-2.0.1.dist-info/WHEEL
tpms-2.0.1.dist-info/entry_points.txt
tpms-2.0.1.dist-info/top_level.txt
tpms-2.0.1.dist-info/RECORD
