Metadata-Version: 2.1
Name: tpms
Version: 2.0.1
Summary: A Python library for interfacing with TPMS (Tire Pressure Monitoring System) devices
Home-page: https://github.com/samskjord/tpms
Author: Sam Conway
Author-email: pypi@invertica.co.uk
Project-URL: Bug Reports, https://github.com/samskjord/tpms/issues
Project-URL: Source, https://github.com/samskjord/tpms
Keywords: tpms,tire pressure,monitoring,sensors,automotive
Classifier: Development Status :: 4 - Beta
Classifier: Intended Audience :: Developers
Classifier: License :: OSI Approved :: MIT License
Classifier: Programming Language :: Python :: 3
Classifier: Programming Language :: Python :: 3.6
Classifier: Programming Language :: Python :: 3.7
Classifier: Programming Language :: Python :: 3.8
Classifier: Programming Language :: Python :: 3.9
Classifier: Programming Language :: Python :: 3.10
Classifier: Topic :: Software Development :: Libraries
Classifier: Topic :: System :: Hardware
Classifier: Topic :: System :: Hardware :: Hardware Drivers
Requires-Python: >=3.6
License-File: LICENSE
Requires-Dist: pyserial>=3.5
